barc4beams/__init__.py
barc4beams/_version.py
barc4beams/adapters.py
barc4beams/beam.py
barc4beams/io.py
barc4beams/misc.py
barc4beams/propagation.py
barc4beams/sampling.py
barc4beams/schema.py
barc4beams/stats.py
barc4beams/viz.py
barc4beams-2025.11.11.dist-info/licenses/LICENSE
barc4beams-2025.11.11.dist-info/METADATA
barc4beams-2025.11.11.dist-info/WHEEL
barc4beams-2025.11.11.dist-info/top_level.txt
barc4beams-2025.11.11.dist-info/RECORD
