Metadata-Version: 2.4
Name: barc4beams
Version: 2025.11.11
Summary: A Python project for: standardization, statistics, and plotting ray-traced photon beams (PyOptiX, SHADOW3/4).
Author-email: Rafael Celestre <rafael.celestre@synchrotron-soleil.fr>
License-Expression: CECILL-2.1
Project-URL: Homepage, https://github.com/barc4/barc4beams
Project-URL: Repository, https://github.com/barc4/barc4beams
Keywords: ray-tracing,beamline design,x-ray optics,optics
Classifier: Programming Language :: Python :: 3
Classifier: Operating System :: OS Independent
Classifier: Intended Audience :: Science/Research
Classifier: Topic :: Scientific/Engineering :: Physics
Requires-Python: >=3.10
License-File: LICENSE
Dynamic: license-file
